COPYING
Makefile
fifo_mod.py
lifo_mod.py
linked_list_mod.py
performance-comparison
setup.py
test-fifo_mod
test-lifo_mod
test-linked_list_mod
this-pylint
linked_list_mod.egg-info/PKG-INFO
linked_list_mod.egg-info/SOURCES.txt
linked_list_mod.egg-info/dependency_links.txt
linked_list_mod.egg-info/top_level.txt