Metadata-Version: 1.1
Name: linked-list-mod
Version: 1.12
Summary: Pure Python linked list module, with lifo (stack) and fifo (queue)
Home-page: http://stromberg.dnsalias.org/~strombrg/linked-list
Author: Daniel Richard Stromberg
Author-email: strombrg@gmail.com
License: Apache v2
Keywords: linked list,stack,queue,lifo,fifo
Platform: Cross platform
Classifier: Development Status :: 5 - Production/Stable
Classifier: Intended Audience :: Developers
Classifier: Programming Language :: Python :: 2
Classifier: Programming Language :: Python :: 3
